hexstyle/__init__.py
hexstyle/hexstyle.py
hexstyle-1.1.1.dist-info/licenses/LICENSE
hexstyle-1.1.1.dist-info/METADATA
hexstyle-1.1.1.dist-info/WHEEL
hexstyle-1.1.1.dist-info/top_level.txt
hexstyle-1.1.1.dist-info/RECORD
