Metadata-Version: 2.4
Name: hexstyle
Version: 1.1.1
Summary: A lightweight Python package that lets you print text in any imaginable color using HEX codes
Home-page: https://github.com/SwezyDev/hexstyle
Author: Swezy
Author-email: swezysoftware@gmail.com
License: MIT
Keywords: python,hex,color,text,printing,terminal,ansi
Classifier: Intended Audience :: Developers
Classifier: Programming Language :: Python :: 3
Classifier: Operating System :: Unix
Classifier: Operating System :: MacOS
Classifier: Operating System :: Microsoft :: Windows
Requires-Python: >=3.9
License-File: LICENSE
Dynamic: license-file
